coinspot/__init__.py
coinspot-1.0.0.dist-info/LICENSE
coinspot-1.0.0.dist-info/METADATA
coinspot-1.0.0.dist-info/WHEEL
coinspot-1.0.0.dist-info/top_level.txt
coinspot-1.0.0.dist-info/RECORD
