Metadata-Version: 2.1
Name: coinspot
Version: 1.0.0
Summary: Wrapper for the Coinspot API
Home-page: https://github.com/AlexVerrico/coinspot
Author: Alex Verrico
Author-email: contact@alexverrico.com
License: UNKNOWN
Project-URL: Bug Tracker, https://github.com/AlexVerrico/coinspot/issues
Platform: UNKNOWN
Classifier: Programming Language :: Python :: 3
Classifier: License :: OSI Approved :: GNU General Public License (GPL)
Classifier: Operating System :: OS Independent
Requires-Python: >=3.7
License-File: LICENSE
Requires-Dist: requests
